{
  "annotations": {
    "list": []
  },
  "editable": true,
  "fiscalYearStartMonth": 0,
  "graphTooltip": 1,
  "id": null,
  "links": [],
  "panels": [
    {
      "datasource": {
        "type": "loki",
        "uid": "loki"
      },
      "fieldConfig": {
        "defaults": {
          "color": {
            "mode": "palette-classic"
          },
          "custom": {
            "axisBorderShow": false,
            "axisCenteredZero": false,
            "axisColorMode": "text",
            "axisLabel": "packets/sec",
            "axisPlacement": "auto",
            "barAlignment": 0,
            "drawStyle": "line",
            "fillOpacity": 10,
            "gradientMode": "none",
            "hideFrom": {
              "tooltip": false,
              "viz": false,
              "legend": false
            },
            "insertNulls": false,
            "lineInterpolation": "linear",
            "lineWidth": 1,
            "pointSize": 5,
            "scaleDistribution": {
              "type": "linear"
            },
            "showPoints": "never",
            "spanNulls": false,
            "stacking": {
              "group": "A",
              "mode": "none"
            },
            "thresholdsStyle": {
              "mode": "off"
            }
          },
          "mappings": [],
          "thresholds": {
            "mode": "absolute",
            "steps": [
              {
                "color": "green",
                "value": null
              }
            ]
          },
          "unit": "short"
        },
        "overrides": []
      },
      "gridPos": {
        "h": 8,
        "w": 12,
        "x": 0,
        "y": 0
      },
      "id": 1,
      "options": {
        "legend": {
          "calcs": [],
          "displayMode": "list",
          "placement": "bottom",
          "showLegend": true
        },
        "tooltip": {
          "mode": "multi",
          "sort": "none"
        }
      },
      "pluginVersion": "10.2.3",
      "targets": [
        {
          "datasource": {
            "type": "loki",
            "uid": "loki"
          },
          "editorMode": "code",
          "expr": "sum by (direction) (rate({job=\"esphome-opentherm\", log_type=\"OT_PKT\"}[1m]))",
          "legendFormat": "{{direction}}",
          "queryType": "range",
          "refId": "A"
        }
      ],
      "title": "OpenTherm Packet Rate",
      "type": "timeseries"
    },
    {
      "datasource": {
        "type": "loki",
        "uid": "loki"
      },
      "fieldConfig": {
        "defaults": {
          "color": {
            "mode": "thresholds"
          },
          "mappings": [],
          "max": 100,
          "min": 0,
          "thresholds": {
            "mode": "absolute",
            "steps": [
              {
                "color": "red",
                "value": null
              },
              {
                "color": "yellow",
                "value": 50
              },
              {
                "color": "green",
                "value": 80
              }
            ]
          },
          "unit": "percent"
        },
        "overrides": []
      },
      "gridPos": {
        "h": 8,
        "w": 12,
        "x": 12,
        "y": 0
      },
      "id": 2,
      "options": {
        "minVizHeight": 75,
        "minVizWidth": 75,
        "orientation": "auto",
        "reduceOptions": {
          "values": false,
          "calcs": [
            "lastNotNull"
          ],
          "fields": ""
        },
        "showThresholdLabels": false,
        "showThresholdMarkers": true,
        "sizing": "auto"
      },
      "pluginVersion": "10.2.3",
      "targets": [
        {
          "datasource": {
            "type": "loki",
            "uid": "loki"
          },
          "editorMode": "code",
          "expr": "(sum(rate({job=\"esphome-opentherm\", cache_hit=\"1\"}[5m])) / sum(rate({job=\"esphome-opentherm\"} |= \"OT_CACHE\"[5m]))) * 100",
          "legendFormat": "Cache Hit %",
          "queryType": "range",
          "refId": "A"
        }
      ],
      "title": "Cache Hit Ratio",
      "type": "gauge"
    },
    {
      "datasource": {
        "type": "loki",
        "uid": "loki"
      },
      "fieldConfig": {
        "defaults": {
          "color": {
            "mode": "palette-classic"
          },
          "custom": {
            "axisBorderShow": false,
            "axisCenteredZero": false,
            "axisColorMode": "text",
            "axisLabel": "Temperature °C",
            "axisPlacement": "auto",
            "barAlignment": 0,
            "drawStyle": "line",
            "fillOpacity": 10,
            "gradientMode": "none",
            "hideFrom": {
              "tooltip": false,
              "viz": false,
              "legend": false
            },
            "insertNulls": false,
            "lineInterpolation": "linear",
            "lineWidth": 1,
            "pointSize": 5,
            "scaleDistribution": {
              "type": "linear"
            },
            "showPoints": "never",
            "spanNulls": false,
            "stacking": {
              "group": "A",
              "mode": "none"
            },
            "thresholdsStyle": {
              "mode": "off"
            }
          },
          "mappings": [],
          "thresholds": {
            "mode": "absolute",
            "steps": [
              {
                "color": "green",
                "value": null
              }
            ]
          },
          "unit": "celsius"
        },
        "overrides": []
      },
      "gridPos": {
        "h": 8,
        "w": 12,
        "x": 0,
        "y": 8
      },
      "id": 3,
      "options": {
        "legend": {
          "calcs": [],
          "displayMode": "list",
          "placement": "bottom",
          "showLegend": true
        },
        "tooltip": {
          "mode": "multi",
          "sort": "none"
        }
      },
      "pluginVersion": "10.2.3",
      "targets": [
        {
          "datasource": {
            "type": "loki",
            "uid": "loki"
          },
          "editorMode": "code",
          "expr": "avg_over_time({job=\"esphome-opentherm\", msg_id=\"1\"} | regexp \"parsed=(?P<temp>-?[\\\\d.]+)\" | unwrap temp [1m])",
          "legendFormat": "TSet (Heating Target)",
          "queryType": "range",
          "refId": "A"
        },
        {
          "datasource": {
            "type": "loki",
            "uid": "loki"
          },
          "editorMode": "code",
          "expr": "avg_over_time({job=\"esphome-opentherm\", msg_id=\"25\"} | regexp \"parsed=(?P<temp>-?[\\\\d.]+)\" | unwrap temp [1m])",
          "hide": false,
          "legendFormat": "Tboiler",
          "queryType": "range",
          "refId": "B"
        },
        {
          "datasource": {
            "type": "loki",
            "uid": "loki"
          },
          "editorMode": "code",
          "expr": "avg_over_time({job=\"esphome-opentherm\", msg_id=\"27\"} | regexp \"parsed=(?P<temp>-?[\\\\d.]+)\" | unwrap temp [1m])",
          "hide": false,
          "legendFormat": "Toutside",
          "queryType": "range",
          "refId": "C"
        }
      ],
      "title": "Temperatures",
      "type": "timeseries"
    },
    {
      "datasource": {
        "type": "loki",
        "uid": "loki"
      },
      "fieldConfig": {
        "defaults": {
          "color": {
            "mode": "palette-classic"
          },
          "custom": {
            "axisBorderShow": false,
            "axisCenteredZero": false,
            "axisColorMode": "text",
            "axisLabel": "errors/min",
            "axisPlacement": "auto",
            "barAlignment": 0,
            "drawStyle": "line",
            "fillOpacity": 10,
            "gradientMode": "none",
            "hideFrom": {
              "tooltip": false,
              "viz": false,
              "legend": false
            },
            "insertNulls": false,
            "lineInterpolation": "linear",
            "lineWidth": 1,
            "pointSize": 5,
            "scaleDistribution": {
              "type": "linear"
            },
            "showPoints": "never",
            "spanNulls": false,
            "stacking": {
              "group": "A",
              "mode": "none"
            },
            "thresholdsStyle": {
              "mode": "off"
            }
          },
          "mappings": [],
          "thresholds": {
            "mode": "absolute",
            "steps": [
              {
                "color": "green",
                "value": null
              },
              {
                "color": "red",
                "value": 1
              }
            ]
          },
          "unit": "short"
        },
        "overrides": []
      },
      "gridPos": {
        "h": 8,
        "w": 12,
        "x": 12,
        "y": 8
      },
      "id": 4,
      "options": {
        "legend": {
          "calcs": [],
          "displayMode": "list",
          "placement": "bottom",
          "showLegend": true
        },
        "tooltip": {
          "mode": "multi",
          "sort": "none"
        }
      },
      "pluginVersion": "10.2.3",
      "targets": [
        {
          "datasource": {
            "type": "loki",
            "uid": "loki"
          },
          "editorMode": "code",
          "expr": "sum(rate({job=\"esphome-opentherm\", valid=\"0\"}[1m])) * 60",
          "legendFormat": "Invalid Responses",
          "queryType": "range",
          "refId": "A"
        },
        {
          "datasource": {
            "type": "loki",
            "uid": "loki"
          },
          "editorMode": "code",
          "expr": "sum(rate({job=\"esphome-opentherm\", rate_limited=\"1\"}[1m])) * 60",
          "hide": false,
          "legendFormat": "Rate Limited",
          "queryType": "range",
          "refId": "B"
        }
      ],
      "title": "Errors & Rate Limiting",
      "type": "timeseries"
    },
    {
      "datasource": {
        "type": "loki",
        "uid": "loki"
      },
      "fieldConfig": {
        "defaults": {
          "color": {
            "mode": "palette-classic"
          },
          "custom": {
            "hideFrom": {
              "tooltip": false,
              "viz": false,
              "legend": false
            }
          },
          "mappings": []
        },
        "overrides": []
      },
      "gridPos": {
        "h": 8,
        "w": 12,
        "x": 0,
        "y": 16
      },
      "id": 5,
      "options": {
        "legend": {
          "displayMode": "list",
          "placement": "bottom",
          "showLegend": true,
          "values": []
        },
        "pieType": "pie",
        "tooltip": {
          "mode": "multi"
        }
      },
      "pluginVersion": "10.2.3",
      "targets": [
        {
          "datasource": {
            "type": "loki",
            "uid": "loki"
          },
          "editorMode": "code",
          "expr": "topk(10, sum by (msg_id) (count_over_time({job=\"esphome-opentherm\", log_type=\"OT_PKT\"}[1h])))",
          "legendFormat": "msg_id={{msg_id}}",
          "queryType": "range",
          "refId": "A"
        }
      ],
      "title": "Top 10 Message IDs (1h)",
      "type": "piechart"
    },
    {
      "datasource": {
        "type": "loki",
        "uid": "loki"
      },
      "fieldConfig": {
        "defaults": {
          "color": {
            "mode": "palette-classic"
          },
          "custom": {
            "axisBorderShow": false,
            "axisCenteredZero": false,
            "axisColorMode": "text",
            "axisLabel": "actions/min",
            "axisPlacement": "auto",
            "barAlignment": 0,
            "drawStyle": "line",
            "fillOpacity": 10,
            "gradientMode": "none",
            "hideFrom": {
              "tooltip": false,
              "viz": false,
              "legend": false
            },
            "insertNulls": false,
            "lineInterpolation": "linear",
            "lineWidth": 1,
            "pointSize": 5,
            "scaleDistribution": {
              "type": "linear"
            },
            "showPoints": "never",
            "spanNulls": false,
            "stacking": {
              "group": "A",
              "mode": "none"
            },
            "thresholdsStyle": {
              "mode": "off"
            }
          },
          "mappings": [],
          "thresholds": {
            "mode": "absolute",
            "steps": [
              {
                "color": "green",
                "value": null
              }
            ]
          },
          "unit": "short"
        },
        "overrides": []
      },
      "gridPos": {
        "h": 8,
        "w": 12,
        "x": 12,
        "y": 16
      },
      "id": 6,
      "options": {
        "legend": {
          "calcs": [],
          "displayMode": "list",
          "placement": "bottom",
          "showLegend": true
        },
        "tooltip": {
          "mode": "multi",
          "sort": "none"
        }
      },
      "pluginVersion": "10.2.3",
      "targets": [
        {
          "datasource": {
            "type": "loki",
            "uid": "loki"
          },
          "editorMode": "code",
          "expr": "sum by (ha_action) (rate({job=\"esphome-opentherm\", log_type=\"HA_CMD\"}[1m])) * 60",
          "legendFormat": "{{ha_action}}",
          "queryType": "range",
          "refId": "A"
        }
      ],
      "title": "Home Assistant Actions",
      "type": "timeseries"
    }
  ],
  "refresh": "10s",
  "schemaVersion": 39,
  "tags": ["esphome", "opentherm", "metrics"],
  "templating": {
    "list": []
  },
  "time": {
    "from": "now-1h",
    "to": "now"
  },
  "timepicker": {},
  "timezone": "",
  "title": "ESPHome OpenTherm - Metrics",
  "uid": "esphome-ot-metrics",
  "version": 0,
  "weekStart": ""
}
